hellp/__init__.py
hellp/factory.py
hellp/pipe.py
hellp/version.py
hellp-0.0.0.dist-info/METADATA
hellp-0.0.0.dist-info/RECORD
hellp-0.0.0.dist-info/WHEEL
hellp-0.0.0.dist-info/top_level.txt
