Metadata-Version: 2.1
Name: hellp
Version: 0.0.0
Summary: Pipe Helper
Home-page: https://github.com/python-pipe/hellp.git
Author: Mohammad Hossein Sekhavat
Author-email: sekhavat17@gmail.com
License: UNKNOWN
Keywords: pipe helper tool magrittr data science
Platform: UNKNOWN
Classifier: Development Status :: 3 - Alpha
Classifier: Intended Audience :: Developers
Classifier: Topic :: Software Development :: Build Tools
Classifier: License :: OSI Approved :: MIT License
Classifier: Programming Language :: Python :: 3
Requires-Dist: toolz (==0.9.0)
Provides-Extra: dev
Requires-Dist: check-manifest; extra == 'dev'
Provides-Extra: test
Requires-Dist: coverage; extra == 'test'
